django_model_fsm/__init__.py
django_model_fsm/dataclasses/__init__.py
django_model_fsm/dataclasses/state_data.py
django_model_fsm/dataclasses/trigger_data.py
django_model_fsm/dataclasses/workflow_data.py
django_model_fsm/fields/__init__.py
django_model_fsm/fields/transition_field.py
django_model_fsm/forms/__init__.py
django_model_fsm/helpers/__init__.py
django_model_fsm/helpers/draw_workflow.py
django_model_fsm/models/__init__.py
django_model_fsm/models/transitions_mixin.py
django_model_fsm-0.1.8.dist-info/METADATA
django_model_fsm-0.1.8.dist-info/WHEEL
django_model_fsm-0.1.8.dist-info/RECORD
