Metadata-Version: 2.1
Name: django-model-fsm
Version: 0.1.8
Summary: A package to use transitions with a Django model.
Home-page: https://bitbucket.org/hespul/django-model-fsm/
License: GPL-3.0-or-later
Author: Alexandre Norman
Author-email: norman@xael.org
Requires-Python: >=3.10,<4.0
Classifier: License :: OSI Approved :: GNU General Public License v3 or later (GPLv3+)
Classifier: Programming Language :: Python :: 3
Classifier: Programming Language :: Python :: 3.10
Classifier: Programming Language :: Python :: 3.11
Classifier: Programming Language :: Python :: 3.12
Requires-Dist: django (>=4)
Requires-Dist: transitions (>=0.9,<0.10)
Project-URL: Repository, https://bitbucket.org/hespul/django-model-fsm/
